{"appliedLayout":"Default_Metro","currentScreen":"sm","settings":{"enable_responsive":"1","show_desktop_switcher":null,"enable_boxed_layout":null,"width_boxed_layout":"990","margin":"","go_to_top":"1","icon_go_to_top":"fa-ban","text_go_to_top":"Go to top","color_go_to_top":"#ffffff","bg_go_to_top":"main","ps_go_to_top":""},"sections":[{"id":"section_header","label":"Header","settings":{"name":"Header","identification_code":"item_195365349558","full_width":null,"enable_sticky":null,"margin":"","padding":"","class":""},"rows":[0]},{"id":"section_promo","label":"Promo","settings":{"name":"Promo","identification_code":"item_541311982414","full_width":"1","enable_sticky":0,"margin":"","padding":"","class":""},"rows":[1]},{"id":"section_content-top","label":"Content-top","settings":{"name":"Content-top","identification_code":"item_258983364108","full_width":null,"enable_sticky":0,"margin":"","padding":"","class":""},"rows":[2]},{"id":"section_content","label":"Content","settings":{"name":"Content","identification_code":"item_1333407628000","full_width":null,"enable_sticky":0,"margin":"","padding":{"top":"20","left":"","right":"","bottom":"20"},"class":""},"rows":[4]},{"id":"section_footer","label":"Footer","settings":{"name":"Footer","identification_code":"item_244223742603","full_width":null,"enable_sticky":0,"margin":{"top":"25"},"padding":{"bottom":"30","top":"40","left":"","right":""},"class":""},"rows":[8,9]},{"id":"section_header-top","settings":{"name":"Header Top","identification_code":"item_132909306147","full_width":1,"enable_sticky":0,"margin":"","padding":"","class":""},"rows":[7],"label":"Header Top"},{"id":"section_content-bottom","settings":{"name":"Content-bottom","identification_code":"item_111284986737","full_width":null,"enable_sticky":0,"margin":"","padding":"","class":""},"rows":[10],"label":"Content-bottom"}],"rows":{"0":{"id":"row_row-0","label":"Row #0","settings":{"name":"Row #0","identification_code":"item_424698071620","margin":"","padding":"","class":"flex flex-items-middle"},"columns":[0,1]},"1":{"id":"row_row-1","label":"Row #1","settings":[],"columns":[2]},"2":{"id":"row_row-2","label":"Row #2","settings":[],"columns":[3]},"4":{"id":"row_row-4","label":"Row #4","settings":{"name":"Row #4","identification_code":"item_428825532332","margin":"","padding":"","class":""},"columns":[9,5,8]},"7":{"id":"row_row-7","settings":{"name":"Row #7"},"columns":[10]},"8":{"id":"row_row-8","settings":{"name":"Row #8"},"columns":[11,12]},"9":{"id":"row_row-9","settings":{"name":"Row #9"},"columns":[13]},"10":{"id":"row_row-10","settings":{"name":"Row #10"},"columns":[14]}},"columns":{"0":{"id":"column_column-0","label":"Column #0","settings":{"name":"Column #0","identification_code":"item_608342220047","margin":"","padding":"","visible_in":["lg","md","sm","xs"],"class":""},"items":[0],"width":{"sm":2,"md":3,"lg":3,"xs":12}},"1":{"id":"column_column-1","label":"Column #1","settings":{"name":"Column #1","identification_code":"item_195883306163","margin":"","padding":"","visible_in":["lg","md","sm","xs"],"class":"mainmenu"},"items":[1],"width":{"sm":10,"md":9,"lg":9,"xs":12}},"2":{"id":"column_column-2","label":"Column #2","settings":[],"items":[2],"width":{"lg":12,"md":12,"sm":12,"xs":12}},"3":{"id":"column_column-3","label":"Column #3","settings":[],"items":[3],"width":{"lg":12,"md":12,"sm":12,"xs":12}},"5":{"id":"column_column-5","label":"Column #5","settings":{"name":"Column #5","identification_code":"item_524498539635","margin":"","padding":"","visible_in":["lg","md","sm","xs"],"class":"sunfw-main-body"},"items":[11,5,12],"width":{"sm":6,"md":6,"lg":6,"xs":12}},"8":{"id":"column_column-8","label":"Column #8","settings":{"name":"Column #8","identification_code":"item_904317675950","margin":"","padding":"","visible_in":["lg","md","sm","xs"],"class":""},"items":[8],"width":{"sm":3,"md":3,"lg":3,"xs":12}},"9":{"id":"column_column-9","label":"Column #9","settings":{"name":"Column #9","identification_code":"item_413655405868","margin":"","padding":"","visible_in":["lg","md","sm","xs"],"class":""},"items":[9],"width":{"sm":3,"md":3,"lg":3,"xs":12}},"10":{"id":"column_column-10","width":{"lg":12},"settings":{"name":"Column #10"},"items":[10]},"11":{"id":"column_column-11","width":{"lg":6,"md":6,"sm":6,"xs":12},"settings":{"name":"Column #11","identification_code":"item_71341605840","margin":"","padding":{"top":"","left":"","right":"25","bottom":""},"visible_in":["lg","md","sm","xs"],"class":""},"items":[13]},"12":{"id":"column_column-12","settings":{"name":"Column #12","identification_code":"item_930385129157","margin":"","padding":{"top":"","left":"25","right":"","bottom":""},"visible_in":["lg","md","sm","xs"],"class":""},"items":[14],"width":{"lg":6,"md":6,"sm":6,"xs":12}},"13":{"id":"column_column-13","width":{"lg":12},"settings":{"name":"Column #13","identification_code":"item_585903503197","margin":{"top":"25","left":"","right":"","bottom":"20"},"padding":"","visible_in":["lg","md","sm","xs"],"class":"text-center"},"items":[15]},"14":{"id":"column_column-14","width":{"lg":12},"settings":{"name":"Column #14"},"items":[16]}},"items":{"0":{"id":"item_logo","type":"logo","label":"Logo","settings":{"name":"Logo","identification_code":"item_921164859092","logo":"templates/jsn_yoyo2_pro/images/logo/logo.png","mobile-logo":"","alt":"","link":"","visible_in":["lg","md","sm","xs"],"class":""}},"1":{"id":"item_menu","type":"menu","label":"Menu","settings":{"name":"Menu","identification_code":"item_274374657601","menu-type":"mainmenu","menu-item":"465","menu-start-level":"1","menu-end-level":"0","menu-show-icon":"1","menu-show-description":"1","menu-show-submenu":"1","menu-sub-effect":"1","menu-mobile-target":1,"visible_in":["lg","md","sm","xs"],"class":""}},"2":{"id":"item_position-promo","type":"module-position","label":"Module Position","settings":{"name":"Position: Promo","identification_code":"item_404595972668","module-position":"promo","visible_in":["lg","md","sm","xs"],"class":""}},"3":{"id":"item_position-content-top","type":"module-position","label":"Module Position","settings":{"name":"Position: Content-top","identification_code":"item_745669583642","module-position":"content-top","visible_in":["lg","md","sm","xs"],"class":""}},"5":{"id":"item_main-body","type":"page-content","label":"Main Body","settings":{"name":"Main Body","identification_code":"item_533575659152","show_on_front_page":"1"}},"8":{"id":"item_position-right","type":"module-position","label":"Module Position","settings":{"name":"Position: Right","identification_code":"item_613205720899","module-position":"right","visible_in":["lg","md","sm","xs"],"class":""}},"9":{"id":"item_position-left","type":"module-position","label":"Module Position","settings":{"name":"Position: Left","identification_code":"item_406666299007","module-position":"left","visible_in":["lg","md","sm","xs"],"class":""}},"10":{"id":"item_position-header-top","type":"module-position","settings":{"name":"Position: Header Top","identification_code":"item_784311328623","module-position":"header-top","visible_in":["lg","md","sm","xs"],"class":""}},"11":{"id":"item_position-mainbody-top","type":"module-position","settings":{"name":"Position: Mainbody Top","identification_code":"item_1020838131626","module-position":"main-body-top","visible_in":["lg","md","sm","xs"],"class":""}},"12":{"id":"item_position-mainbody-bottom","type":"module-position","settings":{"name":"Position: Mainbody Bottom","identification_code":"item_1172082980033","module-position":"main-body-bottom","visible_in":["lg","md","sm","xs"],"class":""}},"13":{"id":"item_position-footer","type":"module-position","settings":{"name":"Position: Footer","identification_code":"item_1138986874394","module-position":"footer","visible_in":["lg","md","sm","xs"],"class":""}},"14":{"id":"item_position-bottom","type":"module-position","settings":{"name":"Position: Bottom","identification_code":"item_79470536728","module-position":"bottom","visible_in":["lg","md","sm","xs"],"class":""}},"15":{"id":"item_social-icons","type":"social-icon","settings":{"name":"Social Icons","identification_code":"item_876554280340","items":[{"icon":"fa fa-facebook","text":"Facebook","title":"","link":""},{"icon":"fa fa-twitter","text":"Twitter","title":"","link":""},{"icon":"fa fa-instagram","text":"Instagram","title":"","link":""}],"color":"#ffffff","size":"32","target":"","visible_in":["lg","md","sm","xs"],"class":"yoyo-social"}},"16":{"id":"item_position-content-bottom","type":"module-position","settings":{"name":"Position: Content-bottom","identification_code":"item_1166125378440","module-position":"content-bottom","visible_in":["lg","md","sm","xs"],"class":""}}},"views":{"main":{"sections":[5,0,1,2,3,6,4]},"top":{"rows":[]},"right":{"rows":[]},"bottom":{"rows":[]},"left":{"rows":[]}},"enable_responsive":"1","show_desktop_switcher":null,"enable_boxed_layout":"1","width_boxed_layout":"990","margin":"","go_to_top":"1","icon_go_to_top":"fa-ban","text_go_to_top":"Go to top","screen":"lg","editing":"item_1"}